odoo/addons/fs_file_demo/README.rst
odoo/addons/fs_file_demo/__init__.py
odoo/addons/fs_file_demo/__manifest__.py
odoo/addons/fs_file_demo/i18n/es.po
odoo/addons/fs_file_demo/i18n/fs_file_demo.pot
odoo/addons/fs_file_demo/i18n/it.po
odoo/addons/fs_file_demo/models/__init__.py
odoo/addons/fs_file_demo/models/fs_file.py
odoo/addons/fs_file_demo/readme/CONTRIBUTORS.md
odoo/addons/fs_file_demo/readme/DESCRIPTION.md
odoo/addons/fs_file_demo/readme/USAGE.md
odoo/addons/fs_file_demo/security/fs_file.xml
odoo/addons/fs_file_demo/static/description/icon.png
odoo/addons/fs_file_demo/static/description/index.html
odoo/addons/fs_file_demo/views/fs_file.xml
odoo_addon_fs_file_demo-17.0.1.0.0.4.dist-info/METADATA
odoo_addon_fs_file_demo-17.0.1.0.0.4.dist-info/WHEEL
odoo_addon_fs_file_demo-17.0.1.0.0.4.dist-info/top_level.txt
odoo_addon_fs_file_demo-17.0.1.0.0.4.dist-info/RECORD
